[
  {
    "name": "Gertrudis",
    "field": "gertrudis",
    "clothes": {
      "all": [
        "rubia",
        "guantes-2",
        "gertrudis",
        "bufandita",
        "cardigan",
        "makeup"
      ]
    }
  },
  {
    "name": "Andiamo",
    "field": "andiamo",
    "clothes": {
      "all": [
        "cono",
        "neon",
        "andi"
      ],
      "any": [
        "zig-zag",
        "galaxy"
      ]
    }
  },
  {
    "name": "Funzo",
    "field": "funzo",
    "clothes": {
      "all": [
        "gorrita",
        "funzo",
        "finzo-0",
        "rapado",
        "finzo-2"
      ]
    }
  },
  {
    "name": "Madre nuclear",
    "field": "madre_nuclear",
    "clothes": {
      "all": [
        "rulos",
        "musculosa-n",
        "guantes",
        "bebe-nuclear"
      ],
      "any": [
        "skirt-2",
        "vestido"
      ]
    }
  },
  {
    "name": "Doraemon",
    "field": "doraemon",
    "clothes": {
      "all": [
        "doraemon",
        "dora_shirt",
        "short-s",
        "pantuflas"
      ]
    }
  },
  {
    "name": "Finzo",
    "field": "finzo",
    "clothes": {
      "all": [
          "perilla",
          "musculosa-n",
          "corto",
          "finzo"
      ]
    }
  },
  {
    "name": "Britney Spears",
    "field": "britney",
    "clothes": {
      "all": [
        "britney-1",
        "britney-2",
        "skirt-2",
        "3-black",
        "mocasines"
      ]
    }
  },
  {
    "name": "Jagger Esland",
    "field": "esland",
    "clothes": {
      "all": [
        "gag",
        "esland",
        "turtle-b",
        "jeans-b",
        "mocasines",
        "manbun"
      ]
    }
  },
  {
    "name": "Jagger profesor",
    "field": "profesor",
    "clothes": {
      "all": [
        "glasses",
        "camisa-w",
        "jeans-b"
      ]
    }
  },
  {
    "name": "Jagger boxeador",
    "field": "boxeador",
    "clothes": {
      "all": [
        "broccli",
        "vendas",
        "cinto",
        "boxeo-1"
      ],
      "any": [
        "trencita",
        "coletita"
      ]
    }
  },
  {
    "name": "Macho alfa total",
    "field": "macho_alfa",
    "clothes": {
      "all": [
        "chaleco",
        "suelto",
        "cadenita",
        "botitas",
        "jeans-b"
      ]
    }
  }
]